pyrocess/__init__.py
pyrocess/decorators/__init__.py
pyrocess/process/__init__.py
pyrocess/strategies/__init__.py
pyrocess-0.0.1.dist-info/METADATA
pyrocess-0.0.1.dist-info/WHEEL
pyrocess-0.0.1.dist-info/top_level.txt
pyrocess-0.0.1.dist-info/RECORD
